duk/__init__.py
duk/cli.py
duk/config.py
duk/date_utils.py
duk/fmp_api.py
duk/indicators.py
duk/logging_config.py
duk/ls_utils.py
duk/rates_utils.py
duk/return_utils.py
duk/stats.py
tb_duk-1.1.0.dist-info/licenses/LICENSE
tb_duk-1.1.0.dist-info/METADATA
tb_duk-1.1.0.dist-info/WHEEL
tb_duk-1.1.0.dist-info/entry_points.txt
tb_duk-1.1.0.dist-info/top_level.txt
tb_duk-1.1.0.dist-info/RECORD
